{
  "last_run": "2026-07-15T11:40:16Z",
  "country": "pan-eu",
  "total_active_jobs": 420,
  "new_jobs_found": 48,
  "sources_checked": 1,
  "sources_succeeded": 1,
  "sources_failed": 0,
  "sources_disabled": 3,
  "relevance_filtered": 6,
  "descriptions_enriched": 0,
  "feeds_generated": 2,
  "run_duration_seconds": 2.7,
  "failed_sources": [],
  "per_source": [
    {
      "name": "UN Job Feed",
      "scraper_type": "rss_feed",
      "status": "success",
      "jobs_found": 466,
      "jobs_after_relevance_filter": 460,
      "descriptions_enriched": 0,
      "duration_seconds": 2.0,
      "notes": "Description enrichment disabled for this source"
    }
  ]
}